notedown/__init__.py
notedown/contentsmanager.py
notedown/main.py
notedown/notedown.py
notedown/templates/markdown.tpl
notedown/templates/markdown_outputs.tpl
d2l_notedown-2.1.0.dist-info/LICENSE
d2l_notedown-2.1.0.dist-info/METADATA
d2l_notedown-2.1.0.dist-info/WHEEL
d2l_notedown-2.1.0.dist-info/entry_points.txt
d2l_notedown-2.1.0.dist-info/top_level.txt
d2l_notedown-2.1.0.dist-info/RECORD
