Metadata-Version: 2.1
Name: d2l-notedown
Version: 2.1.0
Summary: A fork of notedown
Home-page: http://github.com/mli/notedown
Author: Mu Li
Author-email: muli.cmu@gmail.com
License: BSD 2-Clause
Platform: UNKNOWN
Requires-Dist: nbformat
Requires-Dist: nbconvert (>=6.2)
Requires-Dist: pandoc-attributes
Requires-Dist: six
